[
  {
    "lights": [
      {
        "data": {
          "color": [127, 102, 204],
          "fade": 2.0,
          "light": "MagicLightShockHand",
          "radius": 71
        },
        "points": [[0.0, 0.0, 0.0]]
      }
    ],
    "models": [
      "weapons\\boundweapons\\boundarrowflight.nif"
    ]
  },
  {
    "lights": [
      {
        "data": {
          "color": [97, 11, 247],
          "fade": 1.0,
          "light": "MagicLightShockHand",
          "radius": 125
        },
        "points": [[0.0, 4.92, 0.0]]
      }
    ],
    "models": ["dlc01\\effects\\fxdlc1sctreasurebarrier01.nif"]
  },
  {
    "lights": [
      {
        "data": {
          "color": [127, 102, 204],
          "fade": 1.0,
          "light": "MagicLightShockHand",
          "radius": 71
        },
        "points": [[0.0, 0.0, 0.0]]
      }
    ],
    "models": ["dlc02\\weapons\\bounddaggerencheffects.nif"]
  },
  {
    "lights": [
      {
        "data": {
          "color": [127, 102, 204],
          "fade": 1.0,
          "light": "MagicLightShockHand",
          "radius": 71
        },
        "points": [[-0.0, -25.0, -0.0]]
      }
    ],
    "models": [
      "weapons\\boundweapons\\boundarrow.nif"
    ]
  },
  {
    "lights": [
      {
        "data": {
          "color": [127, 102, 204],
          "fade": 2.0,
          "light": "MagicLightShockHand",
          "radius": 71
        },
        "points": [[0.0, 0.0, 0.0]]
      }
    ],
    "models": [
      "weapons\\boundweapons\\boundaxeencheffects.nif",
      "magus\\mysticism\\boundwaraxeencheffects.nif",
      "magus\\mysticism\\maginvboundshield.nif",
      "magus\\mysticism\\boundgreatswordencheffects.nif",
      "magus\\mysticism\\boundmace01.nif",
      "magus\\mysticism\\boundshield.nif",
      "magus\\mysticism\\boundmaceencheffects.nif",
      "magus\\mysticism\\boundwaraxe01.nif",
      "magus\\mysticism\\bounddagger01.nif",
      "magus\\mysticism\\boundwarhammerencheffects.nif"
    ]
  },
  {
    "lights": [
      {
        "data": {
          "color": [127, 102, 204],
          "fade": 2.0,
          "light": "MagicLightShockHand",
          "radius": 71
        },
        "points": [[0.0, 0.0, 0.0]]
      }
    ],
    "models": ["weapons\\boundweapons\\boundbowencheffects.nif"]
  },
  {
    "lights": [
      {
        "data": {
          "color": [127, 102, 204],
          "fade": 2.0,
          "light": "MagicLightShockHand",
          "radius": 71
        },
        "points": [[-4.0, 35.0, 0.0]]
      }
    ],
    "models": ["weapons\\boundweapons\\boundswordencheffects.nif"]
  }
]
